tui_rsync/__init__.py
tui_rsync/cli/__init__.py
tui_rsync/cli/cli.py
tui_rsync/cli/groups/__init__.py
tui_rsync/cli/groups/group_prompt.py
tui_rsync/cli/groups/group_remove.py
tui_rsync/cli/groups/group_show.py
tui_rsync/cli/groups/group_update.py
tui_rsync/cli/groups/groups.py
tui_rsync/cli/label_prompt.py
tui_rsync/cli/path_prompt.py
tui_rsync/cli/rsync.py
tui_rsync/cli/source/__init__.py
tui_rsync/cli/source/source.py
tui_rsync/cli/source/source_remove.py
tui_rsync/cli/source/source_show.py
tui_rsync/cli/source/source_update.py
tui_rsync/cli/sync.py
tui_rsync/config/__init__.py
tui_rsync/config/app.py
tui_rsync/main.py
tui_rsync/models/__init__.py
tui_rsync/models/models.py
tui_rsync-0.8.16.dist-info/COPYING
tui_rsync-0.8.16.dist-info/WHEEL
tui_rsync-0.8.16.dist-info/METADATA
tui_rsync-0.8.16.dist-info/entry_points.txt
tui_rsync-0.8.16.dist-info/RECORD
